MANIFEST.in
README.rst
requirements.txt
setup.py
kabutopy/__init__.py
kabutopy/client.py
kabutopy.egg-info/PKG-INFO
kabutopy.egg-info/SOURCES.txt
kabutopy.egg-info/dependency_links.txt
kabutopy.egg-info/requires.txt
kabutopy.egg-info/top_level.txt