Metadata-Version: 1.1
Name: kabutopy
Version: 1.0.0
Summary: client for the kabuto service
Home-page: https://hg.adimian.com/products/kabutopy
Author: See AUTHORS
Author-email: maarten@adimian.com
License: MIT/Expat
Platform: UNKNOWN
Classifier: Development Status :: 4 - Beta
Classifier: Operating System :: MacOS :: MacOS X
Classifier: Operating System :: Microsoft :: Windows
Classifier: Operating System :: POSIX
Classifier: License :: OSI Approved :: MIT License
Classifier: Programming Language :: Python
Classifier: Programming Language :: Python :: 2.7
Classifier: Programming Language :: Python :: 3.3
Classifier: Programming Language :: Python :: 3.4
